{
    "classes": [
        {
            "className": "zaknavdata",
            "lineNumber": 11,
            "object": true,
            "qualifiedClassName": "zaknavdata",
            "slots": [
                {
                    "access": "public",
                    "arguments": [
                        {
                            "name": "sxnazev",
                            "type": "QString"
                        },
                        {
                            "name": "sxbarva",
                            "type": "QString"
                        },
                        {
                            "name": "sxhindct",
                            "type": "QString"
                        },
                        {
                            "name": "sxblikr",
                            "type": "QString"
                        },
                        {
                            "name": "sxblik1",
                            "type": "QString"
                        },
                        {
                            "name": "sxblik2",
                            "type": "QString"
                        },
                        {
                            "name": "sxdolindc",
                            "type": "QString"
                        },
                        {
                            "name": "sxlinka1",
                            "type": "QString"
                        },
                        {
                            "name": "sxlinka2",
                            "type": "QString"
                        },
                        {
                            "name": "sxvyznam",
                            "type": "QString"
                        }
                    ],
                    "index": 0,
                    "name": "xdata",
                    "returnType": "void"
                },
                {
                    "access": "public",
                    "index": 1,
                    "name": "nazev",
                    "returnType": "QString"
                },
                {
                    "access": "public",
                    "index": 2,
                    "name": "barva",
                    "returnType": "QString"
                },
                {
                    "access": "public",
                    "index": 3,
                    "name": "hindct",
                    "returnType": "QString"
                },
                {
                    "access": "public",
                    "index": 4,
                    "name": "blikr",
                    "returnType": "QString"
                },
                {
                    "access": "public",
                    "index": 5,
                    "name": "blik1",
                    "returnType": "QString"
                },
                {
                    "access": "public",
                    "index": 6,
                    "name": "blik2",
                    "returnType": "QString"
                },
                {
                    "access": "public",
                    "index": 7,
                    "name": "dolindc",
                    "returnType": "QString"
                },
                {
                    "access": "public",
                    "index": 8,
                    "name": "linka1",
                    "returnType": "QString"
                },
                {
                    "access": "public",
                    "index": 9,
                    "name": "linka2",
                    "returnType": "QString"
                },
                {
                    "access": "public",
                    "index": 10,
                    "name": "vyznam",
                    "returnType": "QString"
                }
            ],
            "superClasses": [
                {
                    "access": "public",
                    "name": "QObject"
                }
            ]
        }
    ],
    "inputFile": "zaknavdata.h",
    "outputRevision": 69
}
